{
  "entrypoints": [
    "main"
  ],
  "origins": {
    "2237": [
      2237
    ],
    "6112": [
      543,
      1377,
      1869,
      2066,
      2231,
      2491,
      2621,
      2857,
      3253,
      4574,
      4876,
      5429,
      5799,
      6073,
      7142,
      8224,
      9420,
      6112
    ],
    "8594": [
      1869,
      6061,
      8401,
      8594
    ],
    "17896441": [
      1869,
      8594,
      8401
    ],
    "33178141": [
      2309
    ],
    "main": [
      1869,
      5354,
      8792
    ],
    "runtime~main": [
      1869,
      8792,
      5354
    ],
    "05e8b9ba": [
      1869,
      6112,
      3253
    ],
    "0ce74438": [
      1869,
      3365
    ],
    "0eb9e824": [
      6112,
      4876
    ],
    "11d63dd5": [
      6112,
      2231
    ],
    "126a650c": [
      1869,
      1733
    ],
    "15bf0b1e": [
      3073
    ],
    "1df93b7f": [
      1869,
      4583
    ],
    "1f391b9e": [
      1869,
      8594,
      6061
    ],
    "207614b3": [
      5108
    ],
    "219f48e0": [
      7086
    ],
    "22dd74f7": [
      1567
    ],
    "24f9ccf4": [
      6112,
      7142
    ],
    "270c6556": [
      6112,
      543
    ],
    "27b9741a": [
      1869,
      6112,
      4574
    ],
    "3021cf83": [
      6112,
      2857
    ],
    "3269a7d6": [
      9613
    ],
    "36009dc2": [
      7492
    ],
    "397244cb": [
      6171
    ],
    "469dd090": [
      3013
    ],
    "47b1a3df": [
      6112,
      6073
    ],
    "4e5e73e9": [
      6156
    ],
    "51b447f5": [
      1869,
      4003
    ],
    "5b3aa12b": [
      8628
    ],
    "5e95c892": [
      9647
    ],
    "641b70ff": [
      6997
    ],
    "66038f61": [
      6112,
      1377
    ],
    "69d1c199": [
      9451
    ],
    "755aca34": [
      9600
    ],
    "7b0c42bd": [
      4223
    ],
    "7be55031": [
      5394
    ],
    "820429c2": [
      8437
    ],
    "8626c322": [
      2447
    ],
    "929998ab": [
      6112,
      2066
    ],
    "9472c2ac": [
      304
    ],
    "9937d0f4": [
      6112,
      2621
    ],
    "a486ed51": [
      6112,
      2491
    ],
    "a7456010": [
      1235
    ],
    "a7bd4aaa": [
      7098
    ],
    "a94703ab": [
      1869,
      9048
    ],
    "aba21aa0": [
      5742
    ],
    "aede887b": [
      1869,
      7607
    ],
    "b11c23ff": [
      8841
    ],
    "b636e706": [
      1869,
      7062
    ],
    "bb56318f": [
      6112,
      9420
    ],
    "c7ad9d20": [
      6112,
      5799
    ],
    "cc05c86c": [
      2768
    ],
    "cdacdca8": [
      7866
    ],
    "d2d284ac": [
      7075
    ],
    "d3c3ca18": [
      6041
    ],
    "dda6e511": [
      1869,
      1254
    ],
    "e25ec799": [
      4388
    ],
    "e3aa8df8": [
      4595
    ],
    "eb7371d5": [
      6112,
      5429
    ],
    "efca0bb6": [
      6112,
      8224
    ],
    "f480c67b": [
      1869,
      4081
    ],
    "f8c1e3d4": [
      8857
    ],
    "styles": [
      1254,
      1733,
      3253,
      3365,
      4003,
      4081,
      4574,
      4583,
      5354,
      6061,
      6112,
      7062,
      7607,
      8401,
      8594,
      8792,
      9048,
      1869
    ]
  },
  "assets": {
    "304": {
      "js": [
        {
          "file": "assets/js/9472c2ac.d4771e40.js",
          "hash": "e2d2a35b66978d9e",
          "publicPath": "/assets/js/9472c2ac.d4771e40.js"
        }
      ]
    },
    "543": {
      "js": [
        {
          "file": "assets/js/270c6556.a6a3ef49.js",
          "hash": "615ed702665be4dc",
          "publicPath": "/assets/js/270c6556.a6a3ef49.js"
        }
      ]
    },
    "1235": {
      "js": [
        {
          "file": "assets/js/a7456010.33d37aee.js",
          "hash": "ff58794500609ead",
          "publicPath": "/assets/js/a7456010.33d37aee.js"
        }
      ]
    },
    "1254": {
      "js": [
        {
          "file": "assets/js/dda6e511.41b3a3fe.js",
          "hash": "9fc8e5e03ce51827",
          "publicPath": "/assets/js/dda6e511.41b3a3fe.js"
        }
      ]
    },
    "1377": {
      "js": [
        {
          "file": "assets/js/66038f61.f448f972.js",
          "hash": "47ab7f5aa4771673",
          "publicPath": "/assets/js/66038f61.f448f972.js"
        }
      ]
    },
    "1567": {
      "js": [
        {
          "file": "assets/js/22dd74f7.04b00969.js",
          "hash": "1b5e69ebec27b4a1",
          "publicPath": "/assets/js/22dd74f7.04b00969.js"
        }
      ]
    },
    "1733": {
      "js": [
        {
          "file": "assets/js/126a650c.717af911.js",
          "hash": "1b7bde6676c56aaa",
          "publicPath": "/assets/js/126a650c.717af911.js"
        }
      ]
    },
    "1869": {
      "css": [
        {
          "file": "assets/css/styles.f179bf0d.css",
          "hash": "d7a2a11a2bd30086",
          "publicPath": "/assets/css/styles.f179bf0d.css"
        }
      ]
    },
    "2066": {
      "js": [
        {
          "file": "assets/js/929998ab.019fb715.js",
          "hash": "d03bfaf38da3ba0c",
          "publicPath": "/assets/js/929998ab.019fb715.js"
        }
      ]
    },
    "2231": {
      "js": [
        {
          "file": "assets/js/11d63dd5.5d594505.js",
          "hash": "092022cb5c1020d2",
          "publicPath": "/assets/js/11d63dd5.5d594505.js"
        }
      ]
    },
    "2237": {
      "js": [
        {
          "file": "assets/js/2237.976fbcbd.js",
          "hash": "9c848c805d94999f",
          "publicPath": "/assets/js/2237.976fbcbd.js"
        }
      ]
    },
    "2309": {
      "js": [
        {
          "file": "assets/js/33178141.719ff47b.js",
          "hash": "1f494fbbd69d272e",
          "publicPath": "/assets/js/33178141.719ff47b.js"
        }
      ]
    },
    "2447": {
      "js": [
        {
          "file": "assets/js/8626c322.e0891d38.js",
          "hash": "06a9d38ffadc545c",
          "publicPath": "/assets/js/8626c322.e0891d38.js"
        }
      ]
    },
    "2491": {
      "js": [
        {
          "file": "assets/js/a486ed51.0fa65331.js",
          "hash": "ba76e2bb4dbf3f0a",
          "publicPath": "/assets/js/a486ed51.0fa65331.js"
        }
      ]
    },
    "2621": {
      "js": [
        {
          "file": "assets/js/9937d0f4.cc2420d3.js",
          "hash": "1e2b7e4e25c819e6",
          "publicPath": "/assets/js/9937d0f4.cc2420d3.js"
        }
      ]
    },
    "2768": {
      "js": [
        {
          "file": "assets/js/cc05c86c.9a20a4b0.js",
          "hash": "1601f8c6532c72f3",
          "publicPath": "/assets/js/cc05c86c.9a20a4b0.js"
        }
      ]
    },
    "2857": {
      "js": [
        {
          "file": "assets/js/3021cf83.c6a94c48.js",
          "hash": "7600140f6b30fdbe",
          "publicPath": "/assets/js/3021cf83.c6a94c48.js"
        }
      ]
    },
    "3013": {
      "js": [
        {
          "file": "assets/js/469dd090.69b3f856.js",
          "hash": "5af7a98e1a46a8e8",
          "publicPath": "/assets/js/469dd090.69b3f856.js"
        }
      ]
    },
    "3073": {
      "js": [
        {
          "file": "assets/js/15bf0b1e.25a4299b.js",
          "hash": "9639058d21b94327",
          "publicPath": "/assets/js/15bf0b1e.25a4299b.js"
        }
      ]
    },
    "3253": {
      "js": [
        {
          "file": "assets/js/05e8b9ba.d8674c44.js",
          "hash": "f9df989d58565ccc",
          "publicPath": "/assets/js/05e8b9ba.d8674c44.js"
        }
      ]
    },
    "3365": {
      "js": [
        {
          "file": "assets/js/0ce74438.9d8aed45.js",
          "hash": "c78fcb3ca20436e7",
          "publicPath": "/assets/js/0ce74438.9d8aed45.js"
        }
      ]
    },
    "4003": {
      "js": [
        {
          "file": "assets/js/51b447f5.2529e6e3.js",
          "hash": "a263543c91d8dbc0",
          "publicPath": "/assets/js/51b447f5.2529e6e3.js"
        }
      ]
    },
    "4081": {
      "js": [
        {
          "file": "assets/js/f480c67b.607c9779.js",
          "hash": "9916cc9619740227",
          "publicPath": "/assets/js/f480c67b.607c9779.js"
        }
      ]
    },
    "4223": {
      "js": [
        {
          "file": "assets/js/7b0c42bd.d66bf70e.js",
          "hash": "36c4d7e6832b51ba",
          "publicPath": "/assets/js/7b0c42bd.d66bf70e.js"
        }
      ]
    },
    "4388": {
      "js": [
        {
          "file": "assets/js/e25ec799.569d67b2.js",
          "hash": "9bfd115728b12823",
          "publicPath": "/assets/js/e25ec799.569d67b2.js"
        }
      ]
    },
    "4574": {
      "js": [
        {
          "file": "assets/js/27b9741a.8bfd55a1.js",
          "hash": "6fd4e6e9ca84d83f",
          "publicPath": "/assets/js/27b9741a.8bfd55a1.js"
        }
      ]
    },
    "4583": {
      "js": [
        {
          "file": "assets/js/1df93b7f.48f1a8f7.js",
          "hash": "71fab367f40c7048",
          "publicPath": "/assets/js/1df93b7f.48f1a8f7.js"
        }
      ]
    },
    "4595": {
      "js": [
        {
          "file": "assets/js/e3aa8df8.2bae7975.js",
          "hash": "02624f5980094913",
          "publicPath": "/assets/js/e3aa8df8.2bae7975.js"
        }
      ]
    },
    "4876": {
      "js": [
        {
          "file": "assets/js/0eb9e824.813a0fb0.js",
          "hash": "ce6014f193d2485c",
          "publicPath": "/assets/js/0eb9e824.813a0fb0.js"
        }
      ]
    },
    "5108": {
      "js": [
        {
          "file": "assets/js/207614b3.2a629d9c.js",
          "hash": "dc0f323beadc3e2b",
          "publicPath": "/assets/js/207614b3.2a629d9c.js"
        }
      ]
    },
    "5354": {
      "js": [
        {
          "file": "assets/js/runtime~main.f7b0ca87.js",
          "hash": "2b94728b5b54aa3a",
          "publicPath": "/assets/js/runtime~main.f7b0ca87.js"
        }
      ]
    },
    "5394": {
      "js": [
        {
          "file": "assets/js/7be55031.5c2e8775.js",
          "hash": "136eae6494505b79",
          "publicPath": "/assets/js/7be55031.5c2e8775.js"
        }
      ]
    },
    "5429": {
      "js": [
        {
          "file": "assets/js/eb7371d5.50f67da4.js",
          "hash": "92c0db9fb651a704",
          "publicPath": "/assets/js/eb7371d5.50f67da4.js"
        }
      ]
    },
    "5742": {
      "js": [
        {
          "file": "assets/js/aba21aa0.73356117.js",
          "hash": "bcc9176e8c878d63",
          "publicPath": "/assets/js/aba21aa0.73356117.js"
        }
      ]
    },
    "5799": {
      "js": [
        {
          "file": "assets/js/c7ad9d20.b091dba0.js",
          "hash": "86dbd40055aa2939",
          "publicPath": "/assets/js/c7ad9d20.b091dba0.js"
        }
      ]
    },
    "6041": {
      "js": [
        {
          "file": "assets/js/d3c3ca18.1c460fcd.js",
          "hash": "4057e67a0d3faebc",
          "publicPath": "/assets/js/d3c3ca18.1c460fcd.js"
        }
      ]
    },
    "6061": {
      "js": [
        {
          "file": "assets/js/1f391b9e.53b8c61d.js",
          "hash": "b4b7c429c9d13b07",
          "publicPath": "/assets/js/1f391b9e.53b8c61d.js"
        }
      ]
    },
    "6073": {
      "js": [
        {
          "file": "assets/js/47b1a3df.8576c886.js",
          "hash": "c72b1ca786f424b3",
          "publicPath": "/assets/js/47b1a3df.8576c886.js"
        }
      ]
    },
    "6112": {
      "js": [
        {
          "file": "assets/js/6112.1a4169fe.js",
          "hash": "7f704ba77faf584f",
          "publicPath": "/assets/js/6112.1a4169fe.js"
        }
      ]
    },
    "6156": {
      "js": [
        {
          "file": "assets/js/4e5e73e9.49716157.js",
          "hash": "b2692ef1b00a2700",
          "publicPath": "/assets/js/4e5e73e9.49716157.js"
        }
      ]
    },
    "6171": {
      "js": [
        {
          "file": "assets/js/397244cb.b1693a37.js",
          "hash": "dc2b3858de80bc75",
          "publicPath": "/assets/js/397244cb.b1693a37.js"
        }
      ]
    },
    "6997": {
      "js": [
        {
          "file": "assets/js/641b70ff.8ef9fe97.js",
          "hash": "762d34bfe3b0648d",
          "publicPath": "/assets/js/641b70ff.8ef9fe97.js"
        }
      ]
    },
    "7062": {
      "js": [
        {
          "file": "assets/js/b636e706.0c2fa4d2.js",
          "hash": "5e3fa2f525375e7e",
          "publicPath": "/assets/js/b636e706.0c2fa4d2.js"
        }
      ]
    },
    "7075": {
      "js": [
        {
          "file": "assets/js/d2d284ac.0edb6bbe.js",
          "hash": "fe6ebfa58d061ead",
          "publicPath": "/assets/js/d2d284ac.0edb6bbe.js"
        }
      ]
    },
    "7086": {
      "js": [
        {
          "file": "assets/js/219f48e0.8aff1f75.js",
          "hash": "01db76ca4e707d72",
          "publicPath": "/assets/js/219f48e0.8aff1f75.js"
        }
      ]
    },
    "7098": {
      "js": [
        {
          "file": "assets/js/a7bd4aaa.f57fde5c.js",
          "hash": "f41a12803803325b",
          "publicPath": "/assets/js/a7bd4aaa.f57fde5c.js"
        }
      ]
    },
    "7142": {
      "js": [
        {
          "file": "assets/js/24f9ccf4.f16e6ca6.js",
          "hash": "fd22974d62041c4b",
          "publicPath": "/assets/js/24f9ccf4.f16e6ca6.js"
        }
      ]
    },
    "7492": {
      "js": [
        {
          "file": "assets/js/36009dc2.e97bf9ca.js",
          "hash": "b21c6512ab0391bd",
          "publicPath": "/assets/js/36009dc2.e97bf9ca.js"
        }
      ]
    },
    "7607": {
      "js": [
        {
          "file": "assets/js/aede887b.25f53d58.js",
          "hash": "1bfb9b9431020649",
          "publicPath": "/assets/js/aede887b.25f53d58.js"
        }
      ]
    },
    "7866": {
      "js": [
        {
          "file": "assets/js/cdacdca8.548df0cd.js",
          "hash": "8c8301059932d7d1",
          "publicPath": "/assets/js/cdacdca8.548df0cd.js"
        }
      ]
    },
    "8224": {
      "js": [
        {
          "file": "assets/js/efca0bb6.0f609fe6.js",
          "hash": "563de2e91a4b3504",
          "publicPath": "/assets/js/efca0bb6.0f609fe6.js"
        }
      ]
    },
    "8401": {
      "js": [
        {
          "file": "assets/js/17896441.e9bfe576.js",
          "hash": "738719984f950877",
          "publicPath": "/assets/js/17896441.e9bfe576.js"
        }
      ]
    },
    "8437": {
      "js": [
        {
          "file": "assets/js/820429c2.03d1d89a.js",
          "hash": "db813b38a8ef553b",
          "publicPath": "/assets/js/820429c2.03d1d89a.js"
        }
      ]
    },
    "8594": {
      "js": [
        {
          "file": "assets/js/8594.0cabe7c0.js",
          "hash": "5d89dbf09f7a6e16",
          "publicPath": "/assets/js/8594.0cabe7c0.js"
        }
      ]
    },
    "8628": {
      "js": [
        {
          "file": "assets/js/5b3aa12b.15afc2ca.js",
          "hash": "9d2fae0f2184f24c",
          "publicPath": "/assets/js/5b3aa12b.15afc2ca.js"
        }
      ]
    },
    "8792": {
      "js": [
        {
          "file": "assets/js/main.43fbc332.js",
          "hash": "8577090f933b80ec",
          "publicPath": "/assets/js/main.43fbc332.js"
        }
      ]
    },
    "8841": {
      "js": [
        {
          "file": "assets/js/b11c23ff.1347f809.js",
          "hash": "0c849c20ecd1f428",
          "publicPath": "/assets/js/b11c23ff.1347f809.js"
        }
      ]
    },
    "8857": {
      "js": [
        {
          "file": "assets/js/f8c1e3d4.0178214b.js",
          "hash": "13caebc9690e5b9a",
          "publicPath": "/assets/js/f8c1e3d4.0178214b.js"
        }
      ]
    },
    "9048": {
      "js": [
        {
          "file": "assets/js/a94703ab.60355e8c.js",
          "hash": "d678f0d8bafc982f",
          "publicPath": "/assets/js/a94703ab.60355e8c.js"
        }
      ]
    },
    "9420": {
      "js": [
        {
          "file": "assets/js/bb56318f.14b23b71.js",
          "hash": "380574c2a77b05d0",
          "publicPath": "/assets/js/bb56318f.14b23b71.js"
        }
      ]
    },
    "9451": {
      "js": [
        {
          "file": "assets/js/69d1c199.f705fdb2.js",
          "hash": "66b10173cfbf80fa",
          "publicPath": "/assets/js/69d1c199.f705fdb2.js"
        }
      ]
    },
    "9600": {
      "js": [
        {
          "file": "assets/js/755aca34.3d2e60b1.js",
          "hash": "408d1c42a72259de",
          "publicPath": "/assets/js/755aca34.3d2e60b1.js"
        }
      ]
    },
    "9613": {
      "js": [
        {
          "file": "assets/js/3269a7d6.d87d0e9d.js",
          "hash": "66238e3bf7d4bded",
          "publicPath": "/assets/js/3269a7d6.d87d0e9d.js"
        }
      ]
    },
    "9647": {
      "js": [
        {
          "file": "assets/js/5e95c892.0c7d10d7.js",
          "hash": "4731e6aeef09fd11",
          "publicPath": "/assets/js/5e95c892.0c7d10d7.js"
        }
      ]
    }
  }
}